sharklog/__init__.py
sharklog/formatter.py
sharklog/logging.py
sharklog/settings.py
sharklog/utils.py
sharklog-0.1.2.dist-info/licenses/LICENSE
sharklog-0.1.2.dist-info/METADATA
sharklog-0.1.2.dist-info/WHEEL
sharklog-0.1.2.dist-info/top_level.txt
sharklog-0.1.2.dist-info/RECORD
