Metadata-Version: 2.4
Name: sharklog
Version: 0.1.2
Summary: A Python logging helper
Author-email: Shi Changshan <changshanshi@outlook.com>
License: MIT License
Project-URL: Homepage, https://github.com/Bardreamaster/sharklog
Keywords: logging,helper
Classifier: License :: OSI Approved :: MIT License
Classifier: Programming Language :: Python :: 3
Requires-Python: >=3.10
License-File: LICENSE
Dynamic: license-file
